utils_fei/__init__.py
utils_fei/get_helloworld.py
utils_fei-0.0.1.dist-info/LICENSE
utils_fei-0.0.1.dist-info/METADATA
utils_fei-0.0.1.dist-info/WHEEL
utils_fei-0.0.1.dist-info/top_level.txt
utils_fei-0.0.1.dist-info/RECORD
