Metadata-Version: 2.1
Name: utils-fei
Version: 0.0.1
Summary: python tools for gaofei
Home-page: https://github.com/BigDataFounder/string2date
Author: gaofei
Author-email: 1010155688@qq.com
License: MIT
Platform: UNKNOWN
